symopt/__init__.py
symopt/diffNotation.py
symopt-1.0.0.dist-info/LICENSE
symopt-1.0.0.dist-info/METADATA
symopt-1.0.0.dist-info/WHEEL
symopt-1.0.0.dist-info/top_level.txt
symopt-1.0.0.dist-info/RECORD
